create_django_app_poetry/__init__.py
create_django_app_poetry/main.py
create_django_app_poetry-0.1.1.dist-info/LICENSE
create_django_app_poetry-0.1.1.dist-info/METADATA
create_django_app_poetry-0.1.1.dist-info/WHEEL
create_django_app_poetry-0.1.1.dist-info/entry_points.txt
create_django_app_poetry-0.1.1.dist-info/RECORD
